webduino_generator/__init__.py
webduino_generator/arduino.py
webduino_generator/entrypoint.py
webduino_generator/generator.py
webduino_generator/helper.py
webduino_generator/project.py
webduino_generator/userio.py
webduino_generator/demo/index.html
webduino_generator/templates/WebServer.h
webduino_generator/templates/commands.h
webduino_generator/templates/main.ino
webduino_generator-0.5.dist-info/LICENSE.md
webduino_generator-0.5.dist-info/METADATA
webduino_generator-0.5.dist-info/WHEEL
webduino_generator-0.5.dist-info/entry_points.txt
webduino_generator-0.5.dist-info/top_level.txt
webduino_generator-0.5.dist-info/RECORD
