Metadata-Version: 2.1
Name: webduino-generator
Version: 0.5
Summary: Python program to automatically generate source code for an arduino web server
Home-page: https://github.com/StoneLabs/webduino-generator
Author: Levy Ehrstein
Author-email: levyehrstein@googlemail.com
License: UNLICENSE
Platform: UNKNOWN
Requires-Dist: jinja2
Requires-Dist: rich
Requires-Dist: simple-term-menu
